[
  {
    "language": "Arabic",
    "files": [
      "Genetiv 2_ar.md",
      "Genetiv_ar.md",
      "Grammatikunterricht_ar.md",
      "Infinitiv_um_zu_ar.md",
      "Infinitiv_zu_ar.md",
      "Konjunktiv II_ar.md",
      "Nvv 1_ar.md",
      "Nvv 2_ar.md",
      "Nvv 3_ar.md",
      "Nvv 4_ar.md",
      "Nvv 5_ar.md",
      "Tema 10_ar.md",
      "Tema 11_ar.md",
      "Tema 12_ar.md",
      "Tema 1_ar.md",
      "Tema 2_ar.md",
      "Tema 3_ar.md",
      "Tema 4_ar.md",
      "Tema 5_ar.md",
      "Tema 6_ar.md",
      "Tema 7_ar.md",
      "Tema 8_ar.md",
      "Tema 9_ar.md",
      "ihr_euch_ar.md"
    ]
  },
  {
    "language": "Deutsch",
    "files": [
      "Aktiv A1-B1 Beispiele.md",
      "Aktiv A1-B1 Sprechtraining.md",
      "Aktiv A1-B1 Wichtige Verben.md",
      "Aktiv B2-C1 Satzen.md",
      "Aktiv B2-C1 Sprechtraining v3.md",
      "Genetiv 2.md",
      "Genetiv.md",
      "Grammatikunterricht.md",
      "Infinitiv_um_zu.md",
      "Infinitiv_zu.md",
      "Konjunktiv II.md",
      "Nvv 1.md",
      "Nvv 2.md",
      "Nvv 3.md",
      "Nvv 4.md",
      "Nvv 5.md",
      "Redemittel Aspeckt B1.md",
      "Redemittel Aspeckt B2.md",
      "Redemittel Linie.md",
      "Tema 1.md",
      "Tema 10.md",
      "Tema 11.md",
      "Tema 12.md",
      "Tema 2.md",
      "Tema 3.md",
      "Tema 4.md",
      "Tema 5.md",
      "Tema 6.md",
      "Tema 7.md",
      "Tema 8.md",
      "Tema 9.md",
      "der Vorname.md",
      "ihr_euch.md"
    ]
  },
  {
    "language": "English",
    "files": [
      "Genetiv 2_en.md",
      "Genetiv_en.md",
      "Grammatikunterricht_en.md",
      "Infinitiv_um_zu_en.md",
      "Infinitiv_zu_en.md",
      "Konjunktiv II_en.md",
      "Nvv 1_en.md",
      "Nvv 2_en.md",
      "Nvv 3_en.md",
      "Nvv 4_en.md",
      "Nvv 5_en.md",
      "Tema 10_en.md",
      "Tema 11_en.md",
      "Tema 12_en.md",
      "Tema 1_en.md",
      "Tema 2_en.md",
      "Tema 3_en.md",
      "Tema 4_en.md",
      "Tema 5_en.md",
      "Tema 6_en.md",
      "Tema 7_en.md",
      "Tema 8_en.md",
      "Tema 9_en.md",
      "ihr_euch_en.md"
    ]
  },
  {
    "language": "Kurdish",
    "files": [
      "Genetiv 2_ku.md",
      "Genetiv_ku.md",
      "Grammatikunterricht_ku.md",
      "Infinitiv_um_zu_ku.md",
      "Infinitiv_zu_ku.md",
      "Konjunktiv II_ku.md",
      "Nvv 1_ku.md",
      "Nvv 2_ku.md",
      "Nvv 3_ku.md",
      "Nvv 4_ku.md",
      "Nvv 5_ku.md",
      "Tema 10_ku.md",
      "Tema 11_ku.md",
      "Tema 12_ku.md",
      "Tema 1_ku.md",
      "Tema 2_ku.md",
      "Tema 3_ku.md",
      "Tema 4_ku.md",
      "Tema 5_ku.md",
      "Tema 6_ku.md",
      "Tema 7_ku.md",
      "Tema 8_ku.md",
      "Tema 9_ku.md",
      "ihr_euch_ku.md"
    ]
  },
  {
    "language": "Pashto",
    "files": [
      "Genetiv 2_ps.md",
      "Genetiv_ps.md",
      "Grammatikunterricht_ps.md",
      "Infinitiv_um_zu_ps.md",
      "Infinitiv_zu_ps.md",
      "Konjunktiv II_ps.md",
      "Nvv 1_ps.md",
      "Nvv 2_ps.md",
      "Nvv 3_ps.md",
      "Nvv 4_ps.md",
      "Nvv 5_ps.md",
      "Tema 10_ps.md",
      "Tema 11_ps.md",
      "Tema 12_ps.md",
      "Tema 1_ps.md",
      "Tema 2_ps.md",
      "Tema 3_ps.md",
      "Tema 4_ps.md",
      "Tema 5_ps.md",
      "Tema 6_ps.md",
      "Tema 7_ps.md",
      "Tema 8_ps.md",
      "Tema 9_ps.md",
      "ihr_euch_ps.md"
    ]
  },
  {
    "language": "Persian",
    "files": [
      "Genetiv 2_fa.md",
      "Genetiv_fa.md",
      "Grammatikunterricht_fa.md",
      "Infinitiv_um_zu_fa.md",
      "Infinitiv_zu_fa.md",
      "Konjunktiv II_fa.md",
      "Nvv 1_fa.md",
      "Nvv 2_fa.md",
      "Nvv 3_fa.md",
      "Nvv 4_fa.md",
      "Nvv 5_fa.md",
      "Tema 10_fa.md",
      "Tema 11_fa.md",
      "Tema 12_fa.md",
      "Tema 1_fa.md",
      "Tema 2_fa.md",
      "Tema 3_fa.md",
      "Tema 4_fa.md",
      "Tema 5_fa.md",
      "Tema 6_fa.md",
      "Tema 7_fa.md",
      "Tema 8_fa.md",
      "Tema 9_fa.md",
      "ihr_euch_fa.md"
    ]
  },
  {
    "language": "Russian",
    "files": [
      "Genetiv 2_ru.md",
      "Genetiv_ru.md",
      "Grammatikunterricht_ru.md",
      "Infinitiv_um_zu_ru.md",
      "Infinitiv_zu_ru.md",
      "Konjunktiv II_ru.md",
      "Nvv 1_ru.md",
      "Nvv 2_ru.md",
      "Nvv 3_ru.md",
      "Nvv 4_ru.md",
      "Nvv 5_ru.md",
      "Tema 10_ru.md",
      "Tema 11_ru.md",
      "Tema 12_ru.md",
      "Tema 1_ru.md",
      "Tema 2_ru.md",
      "Tema 3_ru.md",
      "Tema 4_ru.md",
      "Tema 5_ru.md",
      "Tema 6_ru.md",
      "Tema 7_ru.md",
      "Tema 8_ru.md",
      "Tema 9_ru.md",
      "ihr_euch_ru.md"
    ]
  },
  {
    "language": "Somali",
    "files": [
      "Genetiv 2_so.md",
      "Genetiv_so.md",
      "Grammatikunterricht_so.md",
      "Infinitiv_um_zu_so.md",
      "Infinitiv_zu_so.md",
      "Konjunktiv II_so.md",
      "Nvv 1_so.md",
      "Nvv 2_so.md",
      "Nvv 3_so.md",
      "Nvv 4_so.md",
      "Nvv 5_so.md",
      "Tema 10_so.md",
      "Tema 11_so.md",
      "Tema 12_so.md",
      "Tema 1_so.md",
      "Tema 2_so.md",
      "Tema 3_so.md",
      "Tema 4_so.md",
      "Tema 5_so.md",
      "Tema 6_so.md",
      "Tema 7_so.md",
      "Tema 8_so.md",
      "Tema 9_so.md",
      "ihr_euch_so.md"
    ]
  },
  {
    "language": "Test",
    "files": [
      "Module 1.md"
    ]
  },
  {
    "language": "Turkish",
    "files": [
      "Aktiv A1-B1 Beispiele_tr.md",
      "Aktiv A1-B1 Sprechtraining_tr.md",
      "Aktiv B2-C1 Sprechtraining v3_tr.md",
      "Genetiv 2_tr.md",
      "Genetiv_tr.md",
      "Grammatikunterricht_tr.md",
      "Infinitiv_um_zu_tr.md",
      "Infinitiv_zu_tr.md",
      "Konjunktiv II_tr.md",
      "Module 1_tr.md",
      "Nvv 1_tr.md",
      "Nvv 2_tr.md",
      "Nvv 3_tr.md",
      "Nvv 4_tr.md",
      "Nvv 5_tr.md",
      "Tema 10_tr.md",
      "Tema 11_tr.md",
      "Tema 12_tr.md",
      "Tema 1_tr.md",
      "Tema 2_tr.md",
      "Tema 3_tr.md",
      "Tema 4_tr.md",
      "Tema 5_tr.md",
      "Tema 6_tr.md",
      "Tema 7_tr.md",
      "Tema 8_tr.md",
      "Tema 9_tr.md",
      "der Vorname_tr.md",
      "ihr_euch_tr.md"
    ]
  },
  {
    "language": "Ukrainian",
    "files": [
      "Genetiv 2_uk.md",
      "Genetiv_uk.md",
      "Grammatikunterricht_uk.md",
      "Infinitiv_um_zu_uk.md",
      "Infinitiv_zu_uk.md",
      "Konjunktiv II_uk.md",
      "Nvv 1_uk.md",
      "Nvv 2_uk.md",
      "Nvv 3_uk.md",
      "Nvv 4_uk.md",
      "Nvv 5_uk.md",
      "Tema 10_uk.md",
      "Tema 11_uk.md",
      "Tema 12_uk.md",
      "Tema 1_uk.md",
      "Tema 2_uk.md",
      "Tema 3_uk.md",
      "Tema 4_uk.md",
      "Tema 5_uk.md",
      "Tema 6_uk.md",
      "Tema 7_uk.md",
      "Tema 8_uk.md",
      "Tema 9_uk.md",
      "ihr_euch_uk.md"
    ]
  }
]